{"1":{"idUser":"joel","idBook":"10","dateP":1733859025,"dateD":1734186611,"devuelto":true},"2":{"idUser":"joel","idBook":"6","dateP":1733859037,"dateD":1735894582,"devuelto":true},"3":{"idUser":"joel","idBook":"6","dateP":1733859080,"dateD":1734186581,"devuelto":false},"4":{"idUser":"joel","idBook":"1","dateP":1733859148,"dateD":1734186608,"devuelto":true},"5":{"idUser":"Juan","idBook":"4","dateP":1733861614,"dateD":1734186585,"devuelto":true},"6":{"idUser":"Juan","idBook":"1","dateP":1734191207,"dateD":1735894336,"devuelto":true,"0":true},"7":{"idUser":null,"idBook":"8","dateP":1734191448,"dateD":1735487448,"devuelto":false,"0":true},"8":{"idUser":null,"idBook":"8","dateP":1734191775,"dateD":1735487775,"devuelto":false,"0":true},"9":{"idUser":null,"idBook":"8","dateP":1734191776,"dateD":1735487776,"devuelto":false,"0":true},"10":{"idUser":null,"idBook":"8","dateP":1734191776,"dateD":1735487776,"devuelto":false,"0":true},"11":{"idUser":null,"idBook":"8","dateP":1734191776,"dateD":1735487776,"devuelto":false,"0":true},"12":{"idUser":null,"idBook":"10","dateP":1735822976,"dateD":1737118976,"devuelto":false,"0":true},"13":{"idUser":null,"idBook":"10","dateP":1735823033,"dateD":1737119033,"devuelto":false,"0":true},"14":{"idUser":null,"idBook":"10","dateP":1735823044,"dateD":1737119044,"devuelto":false,"0":true},"15":{"idUser":null,"idBook":"10","dateP":1735823067,"dateD":1735894559,"devuelto":true,"0":true},"16":{"idUser":"Juan","idBook":"10","dateP":1735823130,"dateD":1735894351,"devuelto":true,"0":true},"17":{"idUser":"Juan","idBook":"10","dateP":1735823159,"dateD":1737205559,"devuelto":false,"0":true},"18":{"idUser":"Juan","idBook":"10","dateP":1735823160,"dateD":1737119160,"devuelto":false,"0":true},"19":{"idUser":"Juan","idBook":"10","dateP":1735823161,"dateD":1737119161,"devuelto":false,"0":true},"20":{"idUser":"Juan","idBook":"10","dateP":1735823161,"dateD":1737119161,"devuelto":false,"0":true},"21":{"idUser":"Juan","idBook":"10","dateP":1735823161,"dateD":1737119161,"devuelto":false,"0":true},"22":{"idUser":"Juan","idBook":"10","dateP":1735823162,"dateD":1737119162,"devuelto":false,"0":true},"23":{"idUser":null,"idBook":"3","dateP":1735889283,"dateD":1737185283,"devuelto":false,"0":true},"24":{"idUser":"joel","idBook":"3","dateP":1735890199,"dateD":1737186199,"devuelto":false,"0":true},"25":{"idUser":"joel","idBook":"10","dateP":1735890229,"dateD":1737186229,"devuelto":false,"0":true},"26":{"idUser":"joel","idBook":"10","dateP":1735890272,"dateD":1737186272,"devuelto":false,"0":true},"27":{"idUser":"joel","idBook":"5","dateP":1735890323,"dateD":1737186323,"devuelto":false,"0":true},"28":{"idUser":"Juan","idBook":"15","dateP":1735912455,"dateD":1737208455,"devuelto":false,"0":true},"29":{"idUser":"Juan","idBook":"13","dateP":1735912464,"dateD":1737208464,"devuelto":false,"0":true}}